sos_access/__init__.py
sos_access/client.py
sos_access/decorators.py
sos_access/exceptions.py
sos_access/integration_example.py
sos_access/integration_example_nokas.py
sos_access/integration_example_secure.py
sos_access/integration_example_security_assistance.py
sos_access/schemas.py
sos_access/test.py
sos_access/test_nokas.py
sos_access/test_secure.py
sos_access/test_security_assistance.py
test/__init__.py
test/test_alarm_request.py
sos_access-0.0.8.dist-info/LICENSE
sos_access-0.0.8.dist-info/METADATA
sos_access-0.0.8.dist-info/WHEEL
sos_access-0.0.8.dist-info/top_level.txt
sos_access-0.0.8.dist-info/RECORD
