Metadata-Version: 2.1
Name: sos-access
Version: 0.0.8
Summary: Python client for sending alarm information via SOS Access v4
Home-page: https://github.com/pwitab/sos-access
Author: Henrik Palmlund Wahlgren @ Palmlund Wahlgren Innovative Technology AB
Author-email: henrik@pwit.se
License: BSD-3
Keywords: alarm,sos access
Platform: UNKNOWN
Classifier: Development Status :: 3 - Alpha
Classifier: License :: OSI Approved :: BSD License
Classifier: Natural Language :: English
Classifier: Programming Language :: Python
Classifier: Programming Language :: Python :: 3
Classifier: Programming Language :: Python :: 3 :: Only
Classifier: Programming Language :: Python :: 3.6
Classifier: Topic :: Software Development :: Libraries
Requires-Python: >=3.6
Requires-Dist: marshmallow (==3.4.0)
Requires-Dist: xmltodict
